<?xml version="1.0" encoding="UTF-8"?>
<flow id="2c634bce-9772-437e-ae72-2e4b5989088e">
  <descriptionCdata><![CDATA[]]></descriptionCdata>
  <annotation></annotation>
  <name>azuresendmails</name>
  <categories/>
  <inputs/>
  <possibleResponses>
    <opResponse id="be070805-dd5c-4845-a5e1-1c5c6c6aac06">
      <annotation></annotation>
      <name>success</name>
      <isDefault>true</isDefault>
      <onFailure>false</onFailure>
      <type>RESOLVED</type>
      <matchRules/>
    </opResponse>
    <opResponse id="1c7587e2-4507-41f3-ac0b-ed46166dc0da">
      <annotation></annotation>
      <name>failure</name>
      <isDefault>false</isDefault>
      <onFailure>true</onFailure>
      <type>ERROR</type>
      <matchRules/>
    </opResponse>
  </possibleResponses>
  <availableResultExpressions/>
  <resultExpression id="f840babf-ab7e-441c-b431-ce2082cf1a90">
    <annotation></annotation>
    <name>FailureMessage</name>
    <fieldName>FailureMessage</fieldName>
    <sourceType>RAWRESULT</sourceType>
    <filters/>
  </resultExpression>
  <iconSpec id="2006258b-8e71-487c-a6cd-2fae7b0ac657">
    <baseIcon>flow.png</baseIcon>
    <basePath>System</basePath>
    <readOnly>false</readOnly>
    <layers/>
  </iconSpec>
  <callouts/>
  <checkPointFlow>true</checkPointFlow>
  <compatibleRuntimeContext>false</compatibleRuntimeContext>
  <historyCheckPointFlow>true</historyCheckPointFlow>
  <steps>
    <step id="cb857e80-1504-48b9-ab73-2a66fbd2a183">
      <annotation></annotation>
      <name>powershellsendmail</name>
      <bounds>
        <x>191.0</x>
        <y>76.0</y>
      </bounds>
      <layer>-1</layer>
      <hideInbound>false</hideInbound>
      <addResultToRunContext>false</addResultToRunContext>
      <isCriticalStep>false</isCriticalStep>
      <isNonBlocking>false</isNonBlocking>
      <isParallelStep>false</isParallelStep>
      <isSingleResponse>false</isSingleResponse>
      <recordInHistory>false</recordInHistory>
      <recordRawOutput>true</recordRawOutput>
      <recordPrimaryOutput>true</recordPrimaryOutput>
      <checkPointStep>true</checkPointStep>
      <historyCheckPointStep>true</historyCheckPointStep>
      <scriptResultStep>false</scriptResultStep>
      <userPrompt></userPrompt>
      <bindings/>
      <transitions>
        <transition id="91d2632f-4571-4bd1-a560-27ccbe9032a4">
          <annotation></annotation>
          <name>success</name>
          <command>NEXT</command>
          <linkMode>false</linkMode>
          <responseSymbol>success</responseSymbol>
          <shouldHandoff>false</shouldHandoff>
          <transitionValue>0.0</transitionValue>
          <destination>
            <refId>fa3a421a-bd41-40ff-9660-c0f6a2d84dba</refId>
          </destination>
          <source>
            <refId>cb857e80-1504-48b9-ab73-2a66fbd2a183</refId>
          </source>
          <positions>
            <point>
              <x>300.0</x>
              <y>70.0</y>
            </point>
            <point>
              <x>245.0</x>
              <y>298.0</y>
            </point>
          </positions>
          <labelPosition>
            <x>333.0</x>
            <y>0.0</y>
          </labelPosition>
        </transition>
        <transition id="d13978f9-eb15-4f21-91eb-f3ec6e591bd6">
          <annotation></annotation>
          <name>failure</name>
          <command>NEXT</command>
          <linkMode>false</linkMode>
          <responseSymbol>failure</responseSymbol>
          <shouldHandoff>false</shouldHandoff>
          <transitionValue>0.0</transitionValue>
          <destination>
            <refId>ea28c91d-636c-4554-b9f2-ade2595cd6b7</refId>
          </destination>
          <source>
            <refId>cb857e80-1504-48b9-ab73-2a66fbd2a183</refId>
          </source>
          <positions>
            <point>
              <x>300.0</x>
              <y>70.0</y>
            </point>
            <point>
              <x>421.0</x>
              <y>134.0</y>
            </point>
          </positions>
          <labelPosition>
            <x>333.0</x>
            <y>0.0</y>
          </labelPosition>
        </transition>
      </transitions>
      <properties/>
      <opRef>
        <refId>9cf8e1d3-9bea-42e2-a49b-11b43bffad7c</refId>
      </opRef>
      <assignments/>
      <throttleSize>0</throttleSize>
    </step>
    <returnStep id="fa3a421a-bd41-40ff-9660-c0f6a2d84dba">
      <annotation></annotation>
      <name>Resolved : success</name>
      <bounds>
        <x>192.0</x>
        <y>232.0</y>
      </bounds>
      <layer>-1</layer>
      <hideInbound>false</hideInbound>
      <addResultToRunContext>false</addResultToRunContext>
      <isCriticalStep>false</isCriticalStep>
      <isNonBlocking>false</isNonBlocking>
      <isParallelStep>false</isParallelStep>
      <isSingleResponse>false</isSingleResponse>
      <recordInHistory>false</recordInHistory>
      <recordRawOutput>true</recordRawOutput>
      <recordPrimaryOutput>true</recordPrimaryOutput>
      <checkPointStep>true</checkPointStep>
      <historyCheckPointStep>true</historyCheckPointStep>
      <scriptResultStep>false</scriptResultStep>
      <userPrompt></userPrompt>
      <bindings/>
      <transitions>
        <transition id="8c76f3ea-b2f7-452f-8d71-00f368631529">
          <annotation></annotation>
          <name>return</name>
          <command>NEXT</command>
          <linkMode>false</linkMode>
          <responseSymbol>success</responseSymbol>
          <shouldHandoff>false</shouldHandoff>
          <transitionValue>0.0</transitionValue>
          <destination>
            <refId>fa3a421a-bd41-40ff-9660-c0f6a2d84dba</refId>
          </destination>
          <source>
            <refId>fa3a421a-bd41-40ff-9660-c0f6a2d84dba</refId>
          </source>
          <positions/>
        </transition>
      </transitions>
      <properties/>
      <returnStepType>RESOLVED</returnStepType>
      <assignments/>
    </returnStep>
    <returnStep id="ea28c91d-636c-4554-b9f2-ade2595cd6b7">
      <annotation></annotation>
      <name>Error : failure</name>
      <bounds>
        <x>371.0</x>
        <y>75.0</y>
      </bounds>
      <layer>-1</layer>
      <hideInbound>false</hideInbound>
      <addResultToRunContext>false</addResultToRunContext>
      <isCriticalStep>false</isCriticalStep>
      <isNonBlocking>false</isNonBlocking>
      <isParallelStep>false</isParallelStep>
      <isSingleResponse>false</isSingleResponse>
      <recordInHistory>false</recordInHistory>
      <recordRawOutput>true</recordRawOutput>
      <recordPrimaryOutput>true</recordPrimaryOutput>
      <checkPointStep>true</checkPointStep>
      <historyCheckPointStep>true</historyCheckPointStep>
      <scriptResultStep>false</scriptResultStep>
      <userPrompt></userPrompt>
      <bindings/>
      <transitions>
        <transition id="582ec040-3965-4773-82ac-b6bfeb95419b">
          <annotation></annotation>
          <name>return</name>
          <command>NEXT</command>
          <linkMode>false</linkMode>
          <responseSymbol>failure</responseSymbol>
          <shouldHandoff>false</shouldHandoff>
          <transitionValue>0.0</transitionValue>
          <destination>
            <refId>ea28c91d-636c-4554-b9f2-ade2595cd6b7</refId>
          </destination>
          <source>
            <refId>ea28c91d-636c-4554-b9f2-ade2595cd6b7</refId>
          </source>
          <positions/>
        </transition>
      </transitions>
      <properties/>
      <returnStepType>ERROR</returnStepType>
      <assignments/>
    </returnStep>
  </steps>
  <startSteps>cb857e80-1504-48b9-ab73-2a66fbd2a183</startSteps>
</flow>